numba_timer/__init__.py
numba_timer/cuda_timer.py
numba_timer-0.1.2.dist-info/LICENSE
numba_timer-0.1.2.dist-info/METADATA
numba_timer-0.1.2.dist-info/WHEEL
numba_timer-0.1.2.dist-info/top_level.txt
numba_timer-0.1.2.dist-info/RECORD
