Metadata-Version: 2.1
Name: numba-timer
Version: 0.1.2
Summary: A helper package to easily time Numba CUDA GPU events
Home-page: https://github.com/mihi-r/numba_timer
Author: Mihir Patel
Author-email: abc55abc55@gmail.com
License: UNKNOWN
Platform: UNKNOWN
Classifier: Programming Language :: Python :: 3
Classifier: License :: OSI Approved :: MIT License
Classifier: Operating System :: OS Independent
Requires-Python: >=3.6
Requires-Dist: numba (>=0.51.0)
